dc2dr/__init__.py
dc2dr/cli.py
dc2dr/parser.py
dc2dr/sorting.py
dc2dr-0.4.0.dist-info/DESCRIPTION.rst
dc2dr-0.4.0.dist-info/METADATA
dc2dr-0.4.0.dist-info/RECORD
dc2dr-0.4.0.dist-info/WHEEL
dc2dr-0.4.0.dist-info/entry_points.txt
dc2dr-0.4.0.dist-info/metadata.json
dc2dr-0.4.0.dist-info/top_level.txt
