Metadata-Version: 2.0
Name: dc2dr
Version: 0.4.0
Summary: Convert Docker Compose to Docker Run Commands
Home-page: https://github.com/alexhumphreys/dc2dr
Author: Alex Humphreys
Author-email: humphreys.a@gmail.com
License: MIT license
Keywords: dc2dr
Platform: UNKNOWN
Classifier: Development Status :: 2 - Pre-Alpha
Classifier: Intended Audience :: Developers
Classifier: License :: OSI Approved :: MIT License
Classifier: Natural Language :: English
Classifier: Programming Language :: Python :: 2
Classifier: Programming Language :: Python :: 2.6
Classifier: Programming Language :: Python :: 2.7
Classifier: Programming Language :: Python :: 3
Classifier: Programming Language :: Python :: 3.3
Classifier: Programming Language :: Python :: 3.4
Classifier: Programming Language :: Python :: 3.5
Requires-Dist: Click (>=6.0)
Requires-Dist: PyYAML (==3.11)
Requires-Dist: pytsort (==0.1.2)
